Metadata-Version: 1.0
Name: g-tic-tac-toe
Version: 0.4
Summary: play the game tic_tac_toe
Home-page: UNKNOWN
Author: Dhiraj Kumar Chaudhary
Author-email: dhirajc963@gmail.com
License: UNKNOWN
Platform: UNKNOWN
